{
  "docs": {
    "Getting Started": [
      "getting-started/intro",
      "getting-started/installation",
      "getting-started/configuration",
      "getting-started/setting",
      "getting-started/directory-structure"
    ],
    "Core": [
      "core/middleware",
      "core/artisan-console",
      "core/helpers",
      "core/grid-editor",
      "core/media-library",
      "core/widget"
    ],
    "Services": [
      "services/general",
      "services/front-web"
    ],
    "Modules": [
      "modules/general",
      "modules/configuration",
      "modules/database",
      "modules/models",
      "modules/routing",
      "modules/controllers",
      "modules/helpers",
      "modules/compiling-assets",
      "modules/artisan-console",
      "modules/resources",
      "modules/localization",
      "modules/events",
      "modules/complete-guide",
      "modules/for-grid-editor"
    ],
    "Theme": [
      "theme/general",
      "theme/configuration",
      "theme/setting",
      "theme/database",
      "theme/routing",
      "theme/middleware",
      "theme/controllers",
      "theme/views",
      "theme/localization",
      "theme/compiling-assets"
    ],
    "Upgrade Guide": [
      "upgrade-guide/3.0.0-from-2"
    ]
  },
  "docs-other": {
    "First Category": [
      "doc4", "doc5"
    ]
  }
}
